LICENSE
pavement.py
requirements.txt
setup.py
debian/README.Debian
debian/changelog
debian/compat
debian/control
debian/copyright
debian/pycompat
debian/pyversions
debian/rules
djangomarkup/__init__.py
djangomarkup/admin.py
djangomarkup/fields.py
djangomarkup/models.py
djangomarkup/processors.py
djangomarkup/urls.py
djangomarkup/views.py
djangomarkup/widgets.py
djangomarkup.egg-info/PKG-INFO
djangomarkup.egg-info/SOURCES.txt
djangomarkup.egg-info/dependency_links.txt
djangomarkup.egg-info/requires.txt
djangomarkup.egg-info/top_level.txt
djangomarkup/fixtures/initial_data.json
djangomarkup/management/__init__.py
djangomarkup/management/commands/__init__.py
djangomarkup/management/commands/clean_source_texts.py
djangomarkup/management/commands/extract_source_texts.py
docs/Makefile
docs/README
docs/source/conf.py
docs/source/index.rst
setuptools_dummy-0.1.0.4-py2.7.egg/setuptools_dummy.py
setuptools_dummy-0.1.0.4-py2.7.egg/EGG-INFO/PKG-INFO
setuptools_dummy-0.1.0.4-py2.7.egg/EGG-INFO/SOURCES.txt
setuptools_dummy-0.1.0.4-py2.7.egg/EGG-INFO/dependency_links.txt
setuptools_dummy-0.1.0.4-py2.7.egg/EGG-INFO/entry_points.txt
setuptools_dummy-0.1.0.4-py2.7.egg/EGG-INFO/top_level.txt
setuptools_dummy-0.1.0.4-py2.7.egg/EGG-INFO/zip-safe
tests/example_project/__init__.py
tests/example_project/manage.py
tests/example_project/run_tests.py
tests/example_project/urls.py
tests/example_project/exampleapp/__init__.py
tests/example_project/exampleapp/admin.py
tests/example_project/exampleapp/models.py
tests/example_project/exampleapp/fixtures/example_admin_user.json
tests/example_project/settings/__init__.py
tests/example_project/settings/base.py
tests/example_project/settings/config.py
tests/example_project/settings/local.example.py
tests/example_project/settings/logger.conf
tests/example_project/templates/box/box_item_listing.html
tests/example_project/templates/page/_base.html
tests/example_project/templates/page/_base_html.html
tests/example_project/templates/page/_base_layout_standard.html
tests/example_project/templates/page/_base_secondary_col.html
tests/example_project/templates/page/category.html
tests/example_project/templates/page/category/africa/category.html
tests/example_project/tests/__init__.py
tests/example_project/tests/test_admin/__init__.py
tests/example_project/tests/test_admin/helpers.py
tests/example_project/tests/test_admin/test_article_markup.py
tests/unit_project/__init__.py
tests/unit_project/helpers.py
tests/unit_project/manage.py
tests/unit_project/run_tests.py
